[{"eventType":"Departure","timeStamp":"2019-07-04T12:20:57.154Z","flight":"QA124","destination":"Auckland","passengers":"61"},{"eventType":"Departure","timeStamp":"2019-07-13T12:20:57.154Z","flight":"AAV253","destination":"Wellington","passengers":"141"},{"eventType":"Arrival","timeStamp":"2019-07-01T12:20:57.154Z","flight":"AAV253","delayed":"01:20","passengers":"39"},{"eventType":"Arrival","timeStamp":"2019-06-16T12:20:57.154Z","flight":"AAV254","delayed":"06:20","passengers":"244"},{"eventType":"Departure","timeStamp":"2019-06-16T12:20:57.155Z","flight":"QA123","destination":"Adielade","passengers":"145"},{"eventType":"Departure","timeStamp":"2019-07-21T12:20:57.155Z","flight":"NZ733","destination":"Christchurch","passengers":"30"},{"eventType":"Arrival","timeStamp":"2019-06-09T12:20:57.155Z","flight":"QA124","delayed":"08:20","passengers":"87"},{"eventType":"Departure","timeStamp":"2019-06-16T12:20:57.155Z","flight":"QA125","destination":"Adielade","passengers":"225"},{"eventType":"Arrival","timeStamp":"2019-06-20T12:20:57.155Z","flight":"AAV733","delayed":"07:20","passengers":"206"},{"eventType":"Departure","timeStamp":"2019-08-10T12:20:57.155Z","flight":"NZ732","destination":"Wellington","passengers":"265"},{"eventType":"Departure","timeStamp":"2019-06-01T12:20:57.155Z","flight":"AAV254","destination":"Brisbane","passengers":"1"},{"eventType":"Departure","timeStamp":"2019-05-21T12:20:57.155Z","flight":"QA124","destination":"Brisbane","passengers":"298"},{"eventType":"Departure","timeStamp":"2019-07-29T12:20:57.155Z","flight":"AAV253","destination":"Christchurch","passengers":"65"},{"eventType":"Arrival","timeStamp":"2019-06-20T12:20:57.155Z","flight":"AAV255","delayed":"08:20","passengers":"237"},{"eventType":"Arrival","timeStamp":"2019-08-03T12:20:57.155Z","flight":"QA123","delayed":"09:20","passengers":"175"},{"eventType":"Departure","timeStamp":"2019-06-29T12:20:57.155Z","flight":"AAV733","destination":"Adielade","passengers":"48"},{"eventType":"Departure","timeStamp":"2019-05-30T12:20:57.159Z","flight":"NZ732","destination":"Auckland","passengers":"299"},{"eventType":"Departure","timeStamp":"2019-06-30T12:20:57.159Z","flight":"AAV733","destination":"Melbourne","passengers":"264"},{"eventType":"Departure","timeStamp":"2019-06-23T12:20:57.159Z","flight":"AAV734","destination":"Wellington","passengers":"127"},{"eventType":"Arrival","timeStamp":"2019-08-14T12:20:57.159Z","flight":"AAV734","delayed":"04:20","passengers":"70"},{"eventType":"Departure","timeStamp":"2019-06-16T12:20:57.160Z","flight":"AAV253","destination":"Brisbane","passengers":"225"},{"eventType":"Arrival","timeStamp":"2019-08-14T12:20:57.160Z","flight":"QA125","delayed":"09:20","passengers":"299"},{"eventType":"Arrival","timeStamp":"2019-07-13T12:20:57.160Z","flight":"QA125","delayed":"05:20","passengers":"16"},{"eventType":"Departure","timeStamp":"2019-07-16T12:20:57.160Z","flight":"QA123","destination":"Parth","passengers":"75"},{"eventType":"Arrival","timeStamp":"2019-07-22T12:20:57.160Z","flight":"AAV733","delayed":"10:20","passengers":"123"},{"eventType":"Arrival","timeStamp":"2019-06-29T12:20:57.160Z","flight":"AAV255","delayed":"06:20","passengers":"90"},{"eventType":"Departure","timeStamp":"2019-07-05T12:20:57.160Z","flight":"QA125","destination":"Brisbane","passengers":"82"},{"eventType":"Departure","timeStamp":"2019-08-05T12:20:57.160Z","flight":"QA123","destination":"Wellington","passengers":"148"},{"eventType":"Arrival","timeStamp":"2019-06-09T12:20:57.160Z","flight":"QA124","delayed":"08:20","passengers":"189"},{"eventType":"Departure","timeStamp":"2019-06-02T12:20:57.160Z","flight":"AAV254","destination":"Wellington","passengers":"58"},{"eventType":"Departure","timeStamp":"2019-06-21T12:20:57.160Z","flight":"NZ734","destination":"Auckland","passengers":"154"},{"eventType":"Arrival","timeStamp":"2019-07-06T12:20:57.160Z","flight":"QA123","delayed":"07:20","passengers":"3"},{"eventType":"Departure","timeStamp":"2019-07-25T12:20:57.160Z","flight":"AAV254","destination":"Melbourne","passengers":"289"},{"eventType":"Departure","timeStamp":"2019-08-21T12:20:57.160Z","flight":"AAV733","destination":"Melbourne","passengers":"282"},{"eventType":"Arrival","timeStamp":"2019-07-04T12:20:57.160Z","flight":"AAV255","delayed":"09:20","passengers":"136"},{"eventType":"Arrival","timeStamp":"2019-07-24T12:20:57.161Z","flight":"QA124","delayed":"01:20","passengers":"259"},{"eventType":"Arrival","timeStamp":"2019-07-13T12:20:57.161Z","flight":"AAV254","delayed":"10:20","passengers":"167"},{"eventType":"Arrival","timeStamp":"2019-07-07T12:20:57.161Z","flight":"NZ734","delayed":"01:20","passengers":"8"},{"eventType":"Arrival","timeStamp":"2019-07-06T12:20:57.161Z","flight":"AAV255","delayed":"07:20","passengers":"178"},{"eventType":"Departure","timeStamp":"2019-05-27T12:20:57.161Z","flight":"QA125","destination":"Sydney","passengers":"74"},{"eventType":"Departure","timeStamp":"2019-08-03T12:20:57.161Z","flight":"AAV253","destination":"Parth","passengers":"157"},{"eventType":"Departure","timeStamp":"2019-08-02T12:20:57.161Z","flight":"NZ733","destination":"Parth","passengers":"237"},{"eventType":"Departure","timeStamp":"2019-05-25T12:20:57.161Z","flight":"AAV255","destination":"Christchurch","passengers":"18"},{"eventType":"Departure","timeStamp":"2019-08-17T12:20:57.161Z","flight":"QA125","destination":"Wellington","passengers":"106"},{"eventType":"Departure","timeStamp":"2019-08-06T12:20:57.161Z","flight":"QA124","destination":"Auckland","passengers":"30"},{"eventType":"Departure","timeStamp":"2019-07-31T12:20:57.161Z","flight":"QA123","destination":"Adielade","passengers":"13"},{"eventType":"Arrival","timeStamp":"2019-07-31T12:20:57.161Z","flight":"NZ733","delayed":"08:20","passengers":"235"},{"eventType":"Departure","timeStamp":"2019-08-20T12:20:57.161Z","flight":"AAV733","destination":"Melbourne","passengers":"228"},{"eventType":"Arrival","timeStamp":"2019-05-18T12:20:57.161Z","flight":"AAV255","delayed":"06:20","passengers":"297"},{"eventType":"Departure","timeStamp":"2019-06-24T12:20:57.161Z","flight":"QA123","destination":"Auckland","passengers":"228"},{"eventType":"Arrival","timeStamp":"2019-08-17T12:20:57.161Z","flight":"QA123","delayed":"03:20","passengers":"286"},{"eventType":"Arrival","timeStamp":"2019-05-20T12:20:57.161Z","flight":"AAV734","delayed":"07:20","passengers":"20"},{"eventType":"Departure","timeStamp":"2019-07-31T12:20:57.161Z","flight":"QA124","destination":"Adielade","passengers":"103"},{"eventType":"Departure","timeStamp":"2019-06-22T12:20:57.161Z","flight":"QA123","destination":"Parth","passengers":"176"},{"eventType":"Departure","timeStamp":"2019-07-12T12:20:57.161Z","flight":"NZ734","destination":"Brisbane","passengers":"126"},{"eventType":"Arrival","timeStamp":"2019-08-14T12:20:57.161Z","flight":"AAV255","delayed":"03:20","passengers":"39"},{"eventType":"Departure","timeStamp":"2019-06-11T12:20:57.162Z","flight":"QA123","destination":"Adielade","passengers":"169"},{"eventType":"Departure","timeStamp":"2019-06-21T12:20:57.162Z","flight":"AAV254","destination":"Brisbane","passengers":"218"},{"eventType":"Arrival","timeStamp":"2019-07-15T12:20:57.162Z","flight":"QA125","delayed":"01:20","passengers":"229"},{"eventType":"Arrival","timeStamp":"2019-06-30T12:20:57.162Z","flight":"AAV732","delayed":"09:20","passengers":"169"},{"eventType":"Arrival","timeStamp":"2019-06-22T12:20:57.162Z","flight":"NZ732","delayed":"04:20","passengers":"62"},{"eventType":"Departure","timeStamp":"2019-07-04T12:20:57.162Z","flight":"AAV732","destination":"Adielade","passengers":"145"},{"eventType":"Departure","timeStamp":"2019-06-08T12:20:57.162Z","flight":"AAV734","destination":"Brisbane","passengers":"210"},{"eventType":"Departure","timeStamp":"2019-06-15T12:20:57.162Z","flight":"QA125","destination":"Adielade","passengers":"164"},{"eventType":"Arrival","timeStamp":"2019-08-16T12:20:57.162Z","flight":"NZ733","delayed":"10:20","passengers":"28"},{"eventType":"Arrival","timeStamp":"2019-08-19T12:20:57.162Z","flight":"AAV255","delayed":"04:20","passengers":"153"},{"eventType":"Arrival","timeStamp":"2019-06-02T12:20:57.163Z","flight":"AAV254","delayed":"06:20","passengers":"3"},{"eventType":"Arrival","timeStamp":"2019-05-23T12:20:57.165Z","flight":"QA124","delayed":"03:20","passengers":"288"},{"eventType":"Departure","timeStamp":"2019-05-25T12:20:57.165Z","flight":"QA125","destination":"Auckland","passengers":"264"},{"eventType":"Departure","timeStamp":"2019-05-20T12:20:57.165Z","flight":"AAV733","destination":"Sydney","passengers":"191"},{"eventType":"Arrival","timeStamp":"2019-05-25T12:20:57.165Z","flight":"QA125","delayed":"02:20","passengers":"271"},{"eventType":"Arrival","timeStamp":"2019-06-29T12:20:57.165Z","flight":"NZ732","delayed":"06:20","passengers":"257"},{"eventType":"Departure","timeStamp":"2019-08-20T12:20:57.165Z","flight":"QA123","destination":"Wellington","passengers":"131"},{"eventType":"Arrival","timeStamp":"2019-08-07T12:20:57.165Z","flight":"AAV733","delayed":"01:20","passengers":"176"},{"eventType":"Arrival","timeStamp":"2019-07-05T12:20:57.165Z","flight":"AAV253","delayed":"02:20","passengers":"217"},{"eventType":"Arrival","timeStamp":"2019-07-12T12:20:57.165Z","flight":"NZ732","delayed":"06:20","passengers":"210"},{"eventType":"Departure","timeStamp":"2019-08-08T12:20:57.166Z","flight":"QA124","destination":"Auckland","passengers":"148"},{"eventType":"Departure","timeStamp":"2019-08-03T12:20:57.166Z","flight":"AAV253","destination":"Auckland","passengers":"239"},{"eventType":"Departure","timeStamp":"2019-06-12T12:20:57.166Z","flight":"AAV253","destination":"Parth","passengers":"96"},{"eventType":"Arrival","timeStamp":"2019-06-07T12:20:57.166Z","flight":"QA125","delayed":"09:20","passengers":"35"},{"eventType":"Departure","timeStamp":"2019-08-15T12:20:57.166Z","flight":"AAV254","destination":"Melbourne","passengers":"142"},{"eventType":"Departure","timeStamp":"2019-06-04T12:20:57.166Z","flight":"QA125","destination":"Christchurch","passengers":"140"},{"eventType":"Arrival","timeStamp":"2019-07-28T12:20:57.166Z","flight":"AAV253","delayed":"08:20","passengers":"2"},{"eventType":"Departure","timeStamp":"2019-05-15T12:20:57.166Z","flight":"NZ732","destination":"Auckland","passengers":"229"},{"eventType":"Departure","timeStamp":"2019-06-08T12:20:57.166Z","flight":"NZ734","destination":"Christchurch","passengers":"68"},{"eventType":"Arrival","timeStamp":"2019-05-16T12:20:57.166Z","flight":"AAV254","delayed":"02:20","passengers":"263"},{"eventType":"Departure","timeStamp":"2019-06-15T12:20:57.166Z","flight":"NZ733","destination":"Adielade","passengers":"71"},{"eventType":"Departure","timeStamp":"2019-05-17T12:20:57.166Z","flight":"AAV733","destination":"Adielade","passengers":"264"},{"eventType":"Departure","timeStamp":"2019-08-15T12:20:57.166Z","flight":"NZ734","destination":"Brisbane","passengers":"186"},{"eventType":"Departure","timeStamp":"2019-06-28T12:20:57.166Z","flight":"NZ733","destination":"Christchurch","passengers":"172"},{"eventType":"Arrival","timeStamp":"2019-08-17T12:20:57.166Z","flight":"AAV734","delayed":"09:20","passengers":"88"},{"eventType":"Arrival","timeStamp":"2019-06-06T12:20:57.167Z","flight":"QA124","delayed":"06:20","passengers":"207"},{"eventType":"Departure","timeStamp":"2019-06-09T12:20:57.167Z","flight":"AAV253","destination":"Wellington","passengers":"94"},{"eventType":"Arrival","timeStamp":"2019-06-21T12:20:57.167Z","flight":"NZ734","delayed":"02:20","passengers":"280"},{"eventType":"Departure","timeStamp":"2019-08-19T12:20:57.167Z","flight":"NZ734","destination":"Parth","passengers":"104"},{"eventType":"Departure","timeStamp":"2019-06-13T12:20:57.167Z","flight":"AAV255","destination":"Christchurch","passengers":"116"},{"eventType":"Arrival","timeStamp":"2019-06-18T12:20:57.167Z","flight":"NZ734","delayed":"03:20","passengers":"74"},{"eventType":"Arrival","timeStamp":"2019-07-25T12:20:57.167Z","flight":"AAV732","delayed":"03:20","passengers":"19"},{"eventType":"Departure","timeStamp":"2019-07-04T12:20:57.167Z","flight":"AAV253","destination":"Wellington","passengers":"134"},{"eventType":"Arrival","timeStamp":"2019-06-30T12:20:57.167Z","flight":"QA125","delayed":"06:20","passengers":"191"}]